blackduck_metrics/__init__.py
blackduck_metrics/analyzer.py
blackduck_metrics/cli.py
blackduck_metrics/templates/template.html
blackduck_metrics/templates/template_simple.html
blackduck_heatmap_metrics-0.1.8.dist-info/METADATA
blackduck_heatmap_metrics-0.1.8.dist-info/WHEEL
blackduck_heatmap_metrics-0.1.8.dist-info/entry_points.txt
blackduck_heatmap_metrics-0.1.8.dist-info/top_level.txt
blackduck_heatmap_metrics-0.1.8.dist-info/RECORD
