Metadata-Version: 2.4
Name: blackduck-heatmap-metrics
Version: 0.1.8
Summary: Black Duck scan heatmap metrics analyzer with interactive visualizations
Home-page: https://github.com/yourusername/blackduck-heatmap-metrics
Author: Your Name
Author-email: Jouni Lehto <lehto.jouni@gmail.com>
License: MIT
Project-URL: Homepage, https://github.com/lejouni/blackduck_heatmap_metrics
Project-URL: Documentation, https://github.com/lejouni/blackduck_heatmap_metrics#readme
Project-URL: Repository, https://github.com/lejouni/blackduck_heatmap_metrics
Project-URL: Issues, https://github.com/lejouni/blackduck_heatmap_metrics/issues
Keywords: blackduck,security,metrics,analysis,visualization
Classifier: Development Status :: 4 - Beta
Classifier: Intended Audience :: Developers
Classifier: Topic :: Software Development :: Quality Assurance
Classifier: License :: OSI Approved :: MIT License
Classifier: Programming Language :: Python :: 3
Classifier: Programming Language :: Python :: 3.7
Classifier: Programming Language :: Python :: 3.8
Classifier: Programming Language :: Python :: 3.9
Classifier: Programming Language :: Python :: 3.10
Classifier: Programming Language :: Python :: 3.11
Requires-Python: >=3.7
Requires-Dist: pandas>=2.0.0
Requires-Dist: jinja2>=3.1.0
Requires-Dist: plotly>=5.18.0
Requires-Dist: tqdm>=4.65.0
Dynamic: author
Dynamic: home-page
Dynamic: requires-python
